CHANGES.rst
COPYING.txt
MANIFEST.in
README.rst
setup.py
./src/structsize.c
./src/vxrpc_py2.c
src/misc.pxd
src/structsize.c
src/structsize.h
src/version.py
src/vxrpc.pyx
src/vxrpc_py2.c
src/vxrpc_py3.c
src/xmlrpc_c.pxd
src/vxrpc.egg-info/PKG-INFO
src/vxrpc.egg-info/SOURCES.txt
src/vxrpc.egg-info/dependency_links.txt
src/vxrpc.egg-info/top_level.txt