Metadata-Version: 1.1
Name: vxrpc
Version: 0.2.5
Summary: XML-RPC client
Home-page: http://bitbucket.org/klepa/vxrpc
Author: Konstantin Lepa
Author-email: konstantin.lepa@gmail.com
License: MIT
Platform: UNKNOWN
Classifier: Development Status :: 4 - Beta
Classifier: Environment :: Web Environment
Classifier: Intended Audience :: Developers
Classifier: License :: OSI Approved :: MIT License
Classifier: Operating System :: POSIX
Classifier: Programming Language :: Cython
Classifier: Programming Language :: Python
Classifier: Programming Language :: Python :: 3
Classifier: Topic :: Internet
Requires: Cython(>=0.14)
